<NpcData xmlns:xsi="http://www.w3.org/2001/XMLSchema-instance" xsi:schemaLocation="https://vezel.dev/novadrop/dc/NpcData NpcData.xsd" huntingZoneId="518" xmlns="https://vezel.dev/novadrop/dc/NpcData">
    <Template id="1001" name="프레이아 로헨" scale="1" gender="female" race="Highelf" size="medium" shapeId="510060" basicActionId="5100600" class="" spawnScriptId="0" resourceSize="100" resourceType="medium" despawnScriptId="0" collideOnMove="false" dontTurn="false" invincible="true" isObjectNpc="false" isWideBroadcaster="false" questCameraOff="true" villager="true" villagerVolumeActiveRange="0" villagerVolumeHalfHeight="0" villagerVolumeInteractionDist="0" villagerVolumeOffset="">
        <AbnormalityResistanceOverride>
            <Abnormality />
            <Abnormality />
            <Abnormality />
        </AbnormalityResistanceOverride>
        <Aggro />
        <Anger gaugeSize="403799" />
        <NamePlate nameplateHeight="0" />
        <Reaction maxAdditionalGauge="600000" />
        <Stat level="40" def="2000" atk="100" maxHp="10000" />
    </Template>
    <Template id="1002" name="아이크 헤인즈" scale="1" gender="male" race="Human" size="medium" shapeId="203103" basicActionId="5000800" class="" spawnScriptId="0" resourceSize="100" resourceType="medium" despawnScriptId="0" collideOnMove="false" dontTurn="false" invincible="true" isObjectNpc="false" isWideBroadcaster="false" villager="true" villagerVolumeActiveRange="0" villagerVolumeHalfHeight="0" villagerVolumeInteractionDist="0" villagerVolumeOffset="">
        <AbnormalityResistanceOverride>
            <Abnormality />
            <Abnormality />
            <Abnormality />
        </AbnormalityResistanceOverride>
        <Aggro />
        <Anger gaugeSize="403799" />
        <NamePlate nameplateHeight="0" />
        <Reaction maxAdditionalGauge="600000" />
        <Stat level="40" def="2000" atk="100" maxHp="10000" />
    </Template>
    <Template id="1003" name="로아나 화이트리버" scale="1" gender="female" race="Highelf" size="medium" shapeId="203505" basicActionId="5001400" class="" spawnScriptId="0" resourceSize="100" resourceType="medium" despawnScriptId="0" collideOnMove="false" dontTurn="false" invincible="true" isObjectNpc="false" isWideBroadcaster="false" villager="true" villagerVolumeActiveRange="0" villagerVolumeHalfHeight="0" villagerVolumeInteractionDist="0" villagerVolumeOffset="">
        <AbnormalityResistanceOverride>
            <Abnormality />
            <Abnormality />
            <Abnormality />
        </AbnormalityResistanceOverride>
        <Aggro />
        <Anger gaugeSize="403799" />
        <NamePlate nameplateHeight="0" />
        <Reaction maxAdditionalGauge="600000" />
        <Stat level="40" def="2000" atk="100" maxHp="10000" />
    </Template>
    <Template id="1004" name="헬레나 아인스타" scale="1" gender="female" race="Highelf" size="medium" shapeId="510521" basicActionId="5001400" class="" spawnScriptId="0" resourceSize="100" resourceType="medium" despawnScriptId="0" collideOnMove="false" dontTurn="false" invincible="true" isObjectNpc="false" isWideBroadcaster="false" villager="true" villagerVolumeActiveRange="0" villagerVolumeHalfHeight="0" villagerVolumeInteractionDist="0" villagerVolumeOffset="">
        <AbnormalityResistanceOverride>
            <Abnormality />
            <Abnormality />
            <Abnormality />
        </AbnormalityResistanceOverride>
        <Aggro />
        <Anger gaugeSize="403799" />
        <NamePlate nameplateHeight="0" />
        <Reaction maxAdditionalGauge="600000" />
        <Stat level="40" def="2000" atk="100" maxHp="10000" />
    </Template>
    <Template id="1005" name="세인 나크툼" scale="1" gender="male" race="Aman" size="medium" shapeId="510531" basicActionId="5001700" class="" spawnScriptId="0" resourceSize="100" resourceType="medium" despawnScriptId="0" collideOnMove="false" dontTurn="false" invincible="true" isObjectNpc="false" isWideBroadcaster="false" villager="true" villagerVolumeActiveRange="0" villagerVolumeHalfHeight="0" villagerVolumeInteractionDist="0" villagerVolumeOffset="">
        <AbnormalityResistanceOverride>
            <Abnormality />
            <Abnormality />
            <Abnormality />
        </AbnormalityResistanceOverride>
        <Aggro />
        <Anger gaugeSize="403799" />
        <NamePlate nameplateHeight="0" />
        <Reaction maxAdditionalGauge="600000" />
        <Stat level="40" def="2000" atk="100" maxHp="10000" />
    </Template>
    <Template id="1006" name="엘론 골든레이크" scale="1" gender="male" race="Highelf" size="medium" shapeId="510511" basicActionId="5001300" class="" spawnScriptId="0" resourceSize="100" resourceType="medium" despawnScriptId="0" collideOnMove="false" dontTurn="false" invincible="true" isObjectNpc="false" isWideBroadcaster="false" villager="true" villagerVolumeActiveRange="0" villagerVolumeHalfHeight="0" villagerVolumeInteractionDist="0" villagerVolumeOffset="">
        <AbnormalityResistanceOverride>
            <Abnormality />
            <Abnormality />
            <Abnormality />
        </AbnormalityResistanceOverride>
        <Aggro />
        <Anger gaugeSize="403799" />
        <NamePlate nameplateHeight="0" />
        <Reaction maxAdditionalGauge="600000" />
        <Stat level="40" def="2000" atk="100" maxHp="10000" />
    </Template>
    <Template id="1007" name="사령관실 경비병" scale="1" gender="male" race="Highelf" size="medium" shapeId="510580" basicActionId="5001300" class="" spawnScriptId="0" resourceSize="100" resourceType="medium" despawnScriptId="0" collideOnMove="false" dontTurn="false" invincible="true" isObjectNpc="false" isWideBroadcaster="false" villager="true" villagerVolumeActiveRange="0" villagerVolumeHalfHeight="0" villagerVolumeInteractionDist="0" villagerVolumeOffset="">
        <AbnormalityResistanceOverride>
            <Abnormality />
            <Abnormality />
            <Abnormality />
        </AbnormalityResistanceOverride>
        <Aggro />
        <Anger gaugeSize="403799" />
        <NamePlate nameplateHeight="0" />
        <Reaction maxAdditionalGauge="600000" />
        <Stat level="40" def="2000" atk="100" maxHp="10000" />
    </Template>
    <Template id="1008" name="사령관실 경비병" scale="1" gender="female" race="Highelf" size="medium" shapeId="510590" basicActionId="5001400" class="" spawnScriptId="0" resourceSize="100" resourceType="medium" despawnScriptId="0" collideOnMove="false" dontTurn="false" invincible="true" isObjectNpc="false" isWideBroadcaster="false" villager="true" villagerVolumeActiveRange="0" villagerVolumeHalfHeight="0" villagerVolumeInteractionDist="0" villagerVolumeOffset="">
        <AbnormalityResistanceOverride>
            <Abnormality />
            <Abnormality />
            <Abnormality />
        </AbnormalityResistanceOverride>
        <Aggro />
        <Anger gaugeSize="403799" />
        <NamePlate nameplateHeight="0" />
        <Reaction maxAdditionalGauge="600000" />
        <Stat level="40" def="2000" atk="100" maxHp="10000" />
    </Template>
    <Template id="1009" name="유른 실버레인" scale="1" gender="male" race="Highelf" size="medium" shapeId="500356" basicActionId="5001300" class="" spawnScriptId="0" resourceSize="100" resourceType="medium" despawnScriptId="0" collideOnMove="false" dontTurn="false" invincible="true" isObjectNpc="false" isWideBroadcaster="false" villager="true" villagerVolumeActiveRange="0" villagerVolumeHalfHeight="0" villagerVolumeInteractionDist="0" villagerVolumeOffset="">
        <AbnormalityResistanceOverride>
            <Abnormality />
            <Abnormality />
            <Abnormality />
        </AbnormalityResistanceOverride>
        <Aggro />
        <Anger gaugeSize="403799" />
        <NamePlate nameplateHeight="0" />
        <Reaction maxAdditionalGauge="600000" />
        <Stat level="40" def="2000" atk="100" maxHp="10000" />
    </Template>
    <Template id="1010" name="시아라 앳킨" scale="1" gender="female" race="Human" size="medium" shapeId="203104" basicActionId="5001200" class="" spawnScriptId="0" resourceSize="100" resourceType="medium" despawnScriptId="0" collideOnMove="false" dontTurn="false" invincible="true" isObjectNpc="false" isWideBroadcaster="false" villager="true" villagerVolumeActiveRange="0" villagerVolumeHalfHeight="0" villagerVolumeInteractionDist="0" villagerVolumeOffset="">
        <AbnormalityResistanceOverride>
            <Abnormality />
            <Abnormality />
            <Abnormality />
        </AbnormalityResistanceOverride>
        <Aggro />
        <Anger gaugeSize="403799" />
        <NamePlate nameplateHeight="0" />
        <Reaction maxAdditionalGauge="600000" />
        <Stat level="40" def="2000" atk="100" maxHp="10000" />
    </Template>
    <Template id="1012" name="린 제나이스" scale="1" gender="male" race="Highelf" size="medium" shapeId="203501" basicActionId="5001300" class="" spawnScriptId="0" resourceSize="100" resourceType="medium" despawnScriptId="0" collideOnMove="false" dontTurn="false" invincible="true" isObjectNpc="false" isWideBroadcaster="false" villager="true" villagerVolumeActiveRange="0" villagerVolumeHalfHeight="0" villagerVolumeInteractionDist="0" villagerVolumeOffset="">
        <AbnormalityResistanceOverride>
            <Abnormality />
            <Abnormality />
            <Abnormality />
        </AbnormalityResistanceOverride>
        <Aggro />
        <Anger gaugeSize="403799" />
        <NamePlate nameplateHeight="0" />
        <Reaction maxAdditionalGauge="600000" />
        <Stat level="40" def="2000" atk="100" maxHp="10000" />
    </Template>
    <Template id="1013" name="제이크 킨들리" scale="1" gender="male" race="Human" size="medium" shapeId="53003003" basicActionId="5300300" class="" spawnScriptId="0" resourceSize="100" resourceType="medium" despawnScriptId="0" collideOnMove="false" dontTurn="false" invincible="true" isObjectNpc="false" isWideBroadcaster="false" villager="true" villagerVolumeActiveRange="0" villagerVolumeHalfHeight="0" villagerVolumeInteractionDist="0" villagerVolumeOffset="">
        <AbnormalityResistanceOverride>
            <Abnormality />
            <Abnormality />
            <Abnormality />
        </AbnormalityResistanceOverride>
        <Aggro />
        <Anger gaugeSize="403799" />
        <NamePlate nameplateHeight="0" />
        <Reaction maxAdditionalGauge="600000" />
        <Stat level="40" def="2000" atk="100" maxHp="10000" />
    </Template>
    <Template id="1015" name="제프 루어만" scale="1" gender="male" race="Human" size="medium" shapeId="53001008" basicActionId="5300100" class="" spawnScriptId="0" resourceSize="100" resourceType="medium" despawnScriptId="0" collideOnMove="false" dontTurn="false" invincible="true" isObjectNpc="false" isWideBroadcaster="false" villager="true" villagerVolumeActiveRange="0" villagerVolumeHalfHeight="0" villagerVolumeInteractionDist="0" villagerVolumeOffset="">
        <AbnormalityResistanceOverride>
            <Abnormality />
            <Abnormality />
            <Abnormality />
        </AbnormalityResistanceOverride>
        <Aggro />
        <Anger gaugeSize="403799" />
        <NamePlate nameplateHeight="0" />
        <Reaction maxAdditionalGauge="600000" />
        <Stat level="40" def="2000" atk="100" maxHp="10000" />
    </Template>
    <Template id="1016" name="아이만 바타히르" scale="1" gender="male" race="Aman" size="medium" shapeId="530410" basicActionId="5304100" class="" spawnScriptId="0" resourceSize="100" resourceType="medium" despawnScriptId="0" collideOnMove="false" dontTurn="false" invincible="true" isObjectNpc="false" isWideBroadcaster="false" villager="true" villagerVolumeActiveRange="0" villagerVolumeHalfHeight="0" villagerVolumeInteractionDist="0" villagerVolumeOffset="">
        <AbnormalityResistanceOverride>
            <Abnormality />
            <Abnormality />
            <Abnormality />
        </AbnormalityResistanceOverride>
        <Aggro />
        <Anger gaugeSize="403799" />
        <NamePlate nameplateHeight="0" />
        <Reaction maxAdditionalGauge="600000" />
        <Stat level="40" def="2000" atk="100" maxHp="10000" />
    </Template>
    <Template id="1017" name="키르샤 라펠레이트" scale="1" gender="female" race="Highelf" size="medium" shapeId="510591" basicActionId="5105900" class="" spawnScriptId="0" resourceSize="100" resourceType="medium" despawnScriptId="0" collideOnMove="false" dontTurn="false" invincible="true" isObjectNpc="false" isWideBroadcaster="false" villager="true" villagerVolumeActiveRange="0" villagerVolumeHalfHeight="0" villagerVolumeInteractionDist="0" villagerVolumeOffset="">
        <AbnormalityResistanceOverride>
            <Abnormality />
            <Abnormality />
            <Abnormality />
        </AbnormalityResistanceOverride>
        <Aggro />
        <Anger gaugeSize="403799" />
        <NamePlate nameplateHeight="0" />
        <Reaction maxAdditionalGauge="600000" />
        <Stat level="40" def="2000" atk="100" maxHp="10000" />
    </Template>
    <Template id="1018" name="타미라" scale="1" gender="female" race="Castanic" size="medium" shapeId="500222" basicActionId="5001600" class="" spawnScriptId="0" resourceSize="100" resourceType="medium" despawnScriptId="0" collideOnMove="false" dontTurn="false" invincible="true" isObjectNpc="false" isWideBroadcaster="false" villager="true" villagerVolumeActiveRange="0" villagerVolumeHalfHeight="0" villagerVolumeInteractionDist="0" villagerVolumeOffset="">
        <AbnormalityResistanceOverride>
            <Abnormality />
            <Abnormality />
            <Abnormality />
        </AbnormalityResistanceOverride>
        <Aggro />
        <Anger gaugeSize="403799" />
        <NamePlate nameplateHeight="0" deathNameplateHeight="0" />
        <Reaction maxAdditionalGauge="600000" />
        <Stat level="40" def="2000" atk="100" maxHp="10000" />
    </Template>
    <Template id="1019" name="사령관실 경비병" scale="1" race="" size="medium" shapeId="510580" basicActionId="5001300" class="" spawnScriptId="0" resourceSize="100" resourceType="medium" despawnScriptId="0" collideOnMove="false" dontTurn="false" invincible="true" isObjectNpc="false" isWideBroadcaster="false" villager="true" villagerVolumeActiveRange="0" villagerVolumeHalfHeight="0" villagerVolumeInteractionDist="0" villagerVolumeOffset="">
        <AbnormalityResistanceOverride>
            <Abnormality />
            <Abnormality />
            <Abnormality />
        </AbnormalityResistanceOverride>
        <Aggro />
        <Anger gaugeSize="403799" />
        <NamePlate nameplateHeight="0" deathNameplateHeight="0" />
        <Reaction maxAdditionalGauge="600000" />
        <Stat level="40" def="2000" atk="100" maxHp="10000" />
    </Template>
    <Template id="1183" name="미란 쿠벨" scale="1" gender="female" race="Highelf" size="medium" shapeId="500348" basicActionId="5001400" class="" spawnScriptId="0" resourceSize="100" resourceType="medium" despawnScriptId="0" collideOnMove="false" dontTurn="false" invincible="true" isObjectNpc="false" isWideBroadcaster="false" villager="true" villagerVolumeActiveRange="0" villagerVolumeHalfHeight="0" villagerVolumeInteractionDist="0" villagerVolumeOffset="">
        <AbnormalityResistanceOverride>
            <Abnormality />
            <Abnormality />
            <Abnormality />
        </AbnormalityResistanceOverride>
        <Aggro />
        <Anger gaugeSize="403799" />
        <NamePlate nameplateHeight="0" deathNameplateHeight="0" />
        <Reaction maxAdditionalGauge="600000" />
        <Stat level="40" def="2000" atk="100" maxHp="10000" />
    </Template>
    <Template id="1200" name="그레이엄 헤인즈" scale="1" gender="male" race="Human" size="medium" shapeId="510050" basicActionId="5100500" class="" spawnScriptId="6001006" resourceSize="100" resourceType="medium" despawnScriptId="0" balanceType="" collideOnMove="false" dontTurn="false" elite="false" invincible="true" isFreeNamed="false" isObjectNpc="false" isWideBroadcaster="false" partyMember="0" questCameraOff="true" showAggroTarget="false" showBalloonAlways="true" showShorttermTarget="false" villager="true" villagerVolumeActiveRange="0" villagerVolumeHalfHeight="0" villagerVolumeInteractionDist="0" villagerVolumeOffset="">
        <AbnormalityResistanceOverride>
            <Abnormality />
            <Abnormality />
            <Abnormality />
        </AbnormalityResistanceOverride>
        <Aggro />
        <Anger gaugeSize="403799" />
        <BalanceRef ignoreAttr="" />
        <NamePlate nameplateHeight="0" deathNameplateHeight="0" />
        <Reaction maxAdditionalGauge="600000" />
        <Stat level="40" def="2000" atk="100" maxHp="10000" />
    </Template>
    <Template id="1201" name="엘리온 쿠벨" scale="1" gender="male" race="Highelf" size="medium" shapeId="510873" basicActionId="5108700" class="" spawnScriptId="6001007" resourceSize="100" resourceType="medium" despawnScriptId="0" balanceType="" collideOnMove="false" dontTurn="false" elite="false" invincible="true" isFreeNamed="false" isObjectNpc="false" isWideBroadcaster="false" partyMember="0" showAggroTarget="false" showBalloonAlways="true" showShorttermTarget="false" villager="true" villagerVolumeActiveRange="0" villagerVolumeHalfHeight="0" villagerVolumeInteractionDist="0" villagerVolumeOffset="">
        <AbnormalityResistanceOverride>
            <Abnormality />
            <Abnormality />
            <Abnormality />
        </AbnormalityResistanceOverride>
        <Aggro />
        <Anger gaugeSize="403799" />
        <BalanceRef ignoreAttr="" />
        <NamePlate nameplateHeight="0" deathNameplateHeight="0" />
        <Reaction maxAdditionalGauge="600000" />
        <Stat level="40" def="2000" atk="100" maxHp="10000" />
    </Template>
    <Template id="1202" name="에키오르 라펠레이트" scale="1" gender="male" race="Highelf" size="medium" shapeId="510300" basicActionId="5103000" class="" spawnScriptId="6001005" resourceSize="100" resourceType="medium" despawnScriptId="0" balanceType="" collideOnMove="false" dontTurn="false" elite="false" invincible="true" isFreeNamed="false" isObjectNpc="false" isWideBroadcaster="false" partyMember="0" showAggroTarget="false" showBalloonAlways="true" showShorttermTarget="false" villager="true" villagerVolumeActiveRange="0" villagerVolumeHalfHeight="0" villagerVolumeInteractionDist="0" villagerVolumeOffset="">
        <AbnormalityResistanceOverride>
            <Abnormality />
            <Abnormality />
            <Abnormality />
        </AbnormalityResistanceOverride>
        <Aggro />
        <Anger gaugeSize="403799" />
        <BalanceRef ignoreAttr="" />
        <NamePlate nameplateHeight="15" deathNameplateHeight="0" />
        <Reaction maxAdditionalGauge="600000" />
        <Stat level="40" def="2000" atk="100" maxHp="10000" />
    </Template>
    <Template id="1203" name="에키오르가 소환한 이동마법석" scale="0.625" gender="male" race="object" size="medium" shapeId="600920" basicActionId="200010" class="" spawnScriptId="0" resourceSize="100" resourceType="medium" despawnScriptId="0" balanceType="밸런싱 안함" collideOnMove="true" dontTurn="true" elite="false" invincible="true" isFreeNamed="false" isObjectNpc="false" isWideBroadcaster="false" partyMember="1" showAggroTarget="false" showShorttermTarget="false" villager="true">
        <AbnormalityResistanceOverride>
            <Abnormality />
            <Abnormality />
            <Abnormality />
        </AbnormalityResistanceOverride>
        <Aggro />
        <Anger gaugeSize="403799" />
        <BalanceRef ignoreAttr="name,name,partyMember" />
        <NamePlate nameplateHeight="0" deathNameplateHeight="0" />
        <Reaction maxAdditionalGauge="600000" />
        <Stat level="65" def="2000" atk="100" maxHp="10000" />
    </Template>
</NpcData>
